tracrpc/__init__.py
tracrpc/api.py
tracrpc/json_rpc.py
tracrpc/search.py
tracrpc/ticket.py
tracrpc/util.py
tracrpc/web_ui.py
tracrpc/wiki.py
tracrpc/xml_rpc.py
tracrpc/htdocs/rpc.css
tracrpc/htdocs/rpc.js
tracrpc/templates/rpc.html
TracXMLRPC-1.1.9.dist-info/METADATA
TracXMLRPC-1.1.9.dist-info/WHEEL
TracXMLRPC-1.1.9.dist-info/entry_points.txt
TracXMLRPC-1.1.9.dist-info/top_level.txt
TracXMLRPC-1.1.9.dist-info/zip-safe
TracXMLRPC-1.1.9.dist-info/RECORD
