Metadata-Version: 2.1
Name: TracXMLRPC
Version: 1.1.9
Summary: RPC interface to Trac
Home-page: https://trac-hacks.org/wiki/XmlRpcPlugin
Author: Alec Thomas
Author-email: alec@swapoff.org
Maintainer: Odd Simon Simonsen
Maintainer-email: simon-code@bvnetwork.no
License: BSD
Platform: UNKNOWN
Classifier: Framework :: Trac
